RPA/Auth.py
RPA/ENV.py
RPA/Webdriver.py
RPA/__init__.py
RPA/logger.py
RPA/API/Chatwork.py
RPA/API/Slack.py
RPA/API/Twitter.py
RPA/API/__init__.py
RPA/Google/Auth.py
RPA/Google/Drive.py
RPA/Google/GAS.py
RPA/Google/Spreadsheet.py
RPA/Google/Youtube.py
RPA/Google/__init__.py
RPA/Google/PDrive/Drive.py
RPA/Google/PDrive/__init__.py
fepr_py_rpa-1.0.8.dist-info/METADATA
fepr_py_rpa-1.0.8.dist-info/WHEEL
fepr_py_rpa-1.0.8.dist-info/top_level.txt
fepr_py_rpa-1.0.8.dist-info/RECORD
